{ "height":20,
 "layers":[
        {
         "data":[9, 9, 9, 9, 9, 9, 9, 9, 9, 9, 9, 9, 9, 9, 9, 9, 9, 9, 9, 9, 9, 9, 9, 9, 9, 9, 9, 9, 9, 9, 9, 9, 9, 9, 9, 9, 9, 9, 9, 9, 9, 9, 9, 9, 9, 9, 9, 9, 9, 9, 9, 9, 9, 9, 9, 9, 9, 9, 9, 9, 9, 9, 9, 9, 9, 9, 9, 9, 9, 9, 9, 9, 9, 9, 9, 9, 9, 9, 9, 9, 9, 9, 9, 9, 9, 9, 9, 9, 9, 9, 9, 9, 9, 9, 9, 9, 9, 9, 9, 9, 9, 9, 9, 9, 9, 9, 9, 9, 9, 9, 9, 9, 9, 9, 9, 9, 9, 9, 9, 9, 9, 9, 9, 9, 9, 9, 9, 9, 9, 9, 9, 9, 9, 9, 9, 9, 9, 9, 9, 9, 9, 9, 9, 9, 9, 9, 9, 9, 9, 9, 9, 9, 9, 9, 9, 9, 9, 9, 9, 9, 9, 9, 9, 9, 9, 9, 9, 9, 9, 9, 9, 9, 9, 9, 9, 9, 9, 9, 9, 9, 9, 9, 9, 9, 9, 9, 9, 9, 9, 9, 9, 9, 9, 9, 9, 9, 9, 9, 9, 9, 9, 9, 9, 9, 9, 9, 9, 9, 9, 9, 9, 9, 9, 9, 9, 9, 9, 9, 9, 9, 9, 9, 9, 9, 9, 9, 9, 9, 9, 9, 9, 9, 9, 9, 9, 9, 9, 9, 9, 9, 9, 9, 9, 9, 9, 9, 9, 9, 9, 9, 9, 9, 9, 9, 9, 9, 9, 9, 9, 9, 9, 9, 9, 9, 9, 9, 9, 9, 9, 9, 9, 9, 9, 9, 9, 9, 9, 9, 9, 9, 9, 9, 9, 9, 9, 9, 9, 9, 9, 9, 9, 9, 9, 9, 9, 9, 9, 9, 9, 9, 9, 9, 9, 9, 9, 9, 9, 9, 9, 9, 9, 9, 9, 9, 9, 9, 9, 9, 9, 9, 9, 9, 9, 9, 9, 9, 9, 9, 9, 9, 9, 9, 9, 9, 9, 9, 9, 9, 9, 9, 9, 9, 9, 9, 9, 9, 9, 9, 9, 9, 9, 9, 9, 9, 9, 9, 9, 9, 9, 9, 9, 9, 9, 9, 9, 9, 9, 9, 9, 9, 9, 9, 9, 9, 9, 9, 9, 9, 9, 9, 9, 9, 9, 9, 9, 9, 9, 9, 9, 9, 9, 9, 9, 9, 9, 9, 9, 9, 9, 9, 9, 9, 9, 9, 9, 9, 9, 9, 9, 9, 9, 9, 9, 9, 9, 9, 9, 9, 9, 9, 9, 9, 9, 9, 9, 9, 9, 9, 9, 9, 9, 9, 9, 9, 9, 9, 9, 9, 9, 9, 9, 9, 9, 9, 9, 9, 9, 9, 9, 9, 9, 9, 9, 9, 9, 9, 9, 9, 9, 9, 9, 9, 9, 9, 9, 9, 9, 9, 9, 9, 9, 9, 9, 9, 9, 9, 9, 9, 9, 9, 9, 9, 9, 9, 9, 9, 9, 9, 9, 9, 9, 9, 9, 9, 9, 9, 9, 9, 9, 9, 9, 9, 9, 9, 9, 9, 9, 9, 9, 9, 9, 9, 9, 9, 9, 9, 9, 9, 9, 9, 9, 9, 9, 9, 9, 9, 9, 9, 9, 9, 9, 9, 9, 9, 9, 9, 9, 9, 9, 9, 9, 9, 9, 9, 9, 9, 9, 9, 9, 9, 9, 9, 9, 9, 9, 9, 9, 9, 9, 9, 9, 9, 9, 9, 9, 9, 9, 9, 9, 9, 9, 9, 9, 9, 9, 9, 9, 9, 9, 9, 9, 9, 9, 9, 9, 9, 9, 9, 9, 9, 9, 9, 9, 9, 9, 9, 9, 9, 9, 9, 9, 9, 9, 9, 9, 9, 9, 9, 9, 9, 9, 9, 9, 9, 9, 9, 9, 9, 9, 9, 9, 9, 9, 9, 9, 9, 9, 9, 9, 9, 9, 9, 9, 9, 9, 9, 9, 9, 9, 9, 9, 9, 62, 62, 62, 62, 62, 9, 9, 9, 9, 9, 9, 9, 9, 9, 9, 9, 9, 9, 9, 9, 9, 9, 9, 9, 9, 9, 9, 9, 9, 9, 9, 9, 9, 9, 9, 9, 9, 9, 9, 9, 9, 9, 9, 9, 9, 9, 9, 9, 9, 9, 9, 9, 9, 9, 9, 9, 9, 9, 9, 9, 9, 9, 9, 9, 9, 9, 9, 9, 9, 9, 9, 9, 9, 9, 9, 9, 9, 9, 9, 9, 9, 9, 9, 9, 9, 9, 9, 9, 214, 214, 9, 9, 9, 9, 9, 9, 9, 9, 9, 62, 62, 62, 62, 62, 62, 62, 9, 9, 9, 9, 9, 9, 9, 9, 9, 9, 9, 9, 9, 214, 9, 9, 9, 9, 9, 9, 9, 9, 9, 9, 9, 9, 9, 9, 9, 9, 9, 9, 9, 9, 9, 9, 9, 9, 9, 9, 9, 9, 9, 9, 9, 9, 9, 9, 9, 9, 9, 9, 9, 9, 9, 9, 9, 9, 9, 9, 9, 9, 9, 9, 9, 9, 9, 9, 9, 9, 9, 9, 9, 151, 152, 9, 9, 9, 9, 9, 879, 880, 1218, 1219, 9, 9, 9, 9, 9, 9, 9, 151, 152, 9, 9, 9, 9, 9, 9, 9, 9, 9, 9, 9, 9, 9, 9, 9, 9, 9, 9, 9, 9, 9, 9, 9, 9, 9, 9, 9, 9, 9, 9, 224, 225, 9, 9, 9, 9, 9, 952, 953, 1291, 1292, 9, 9, 9, 9, 9, 9, 9, 224, 225, 9, 9, 9, 9, 9, 9, 9, 9, 9, 1304, 1304, 1304, 1304, 1304, 1304, 1304, 1304, 1304, 1304, 1304, 1304, 1304, 1304, 1304, 1304, 1304, 1304, 1304, 1304, 1304, 1304, 1304, 9, 9, 1304, 1304, 1304, 1304, 1304, 1304, 1304, 1304, 1304, 1304, 1304, 1304, 9, 9, 1304, 1304, 1304, 1304, 1304, 1304, 1304, 1304, 1304, 1304, 1304, 1377, 1377, 1377, 1377, 1377, 1377, 1377, 1377, 1377, 1377, 1377, 1377, 1377, 1377, 1377, 1377, 1377, 1377, 1377, 1377, 1377, 1377, 1377, 9, 9, 1377, 1377, 1377, 1377, 1377, 1377, 1377, 1377, 1377, 1377, 1377, 1377, 9, 9, 1377, 1377, 1377, 1377, 1377, 1377, 1377, 1377, 1377, 1377, 1377],
         "height":20,
         "name":"Layer1",
         "opacity":1,
         "type":"tilelayer",
         "visible":true,
         "width":50,
         "x":0,
         "y":0
        },
        {
         "draworder":"topdown",
         "height":20,
         "name":"Box",
         "objects":[
                {
                 "height":0,
                 "id":24,
                 "name":"",
                 "polyline":[
                        {
                         "x":0,
                         "y":0
                        },
                        {
                         "x":366.956369063296,
                         "y":0.877886050390657
                        },
                        {
                         "x":366.956369063296,
                         "y":30.7260117636731
                        },
                        {
                         "x":-0.877886050390659,
                         "y":31.6038978140638
                        },
                        {
                         "x":0.877886050390659,
                         "y":1.75577210078131
                        }],
                 "rotation":0,
                 "type":"",
                 "visible":true,
                 "width":0,
                 "x":0,
                 "y":288.824510578527
                },
                {
                 "height":0,
                 "id":25,
                 "name":"",
                 "polyline":[
                        {
                         "x":0,
                         "y":0
                        },
                        {
                         "x":0,
                         "y":14.6600696353308
                        },
                        {
                         "x":14.6600696353308,
                         "y":14.6600696353308
                        },
                        {
                         "x":14.6600696353308,
                         "y":-0.916254352208171
                        },
                        {
                         "x":0,
                         "y":-0.916254352208171
                        }],
                 "rotation":0,
                 "type":"",
                 "visible":true,
                 "width":0,
                 "x":175.920835623969,
                 "y":241.891148982958
                },
                {
                 "height":0,
                 "id":26,
                 "name":"",
                 "polyline":[
                        {
                         "x":0,
                         "y":0
                        },
                        {
                         "x":0.916254352208171,
                         "y":-32.9851566794942
                        },
                        {
                         "x":30.2363936228697,
                         "y":-32.9851566794942
                        },
                        {
                         "x":31.1526479750779,
                         "y":0.916254352208171
                        }],
                 "rotation":0,
                 "type":"",
                 "visible":true,
                 "width":0,
                 "x":335.349092908191,
                 "y":289.536375297783
                },
                {
                 "height":0,
                 "id":27,
                 "name":"",
                 "polyline":[
                        {
                         "x":0,
                         "y":0
                        },
                        {
                         "x":0,
                         "y":-29.3201392706616
                        },
                        {
                         "x":47.645226314825,
                         "y":-29.3201392706616
                        },
                        {
                         "x":47.645226314825,
                         "y":-62.3052959501558
                        },
                        {
                         "x":112.699285321605,
                         "y":-62.3052959501558
                        },
                        {
                         "x":112.699285321605,
                         "y":-31.1526479750779
                        },
                        {
                         "x":190.5809052593,
                         "y":-30.2363936228697
                        },
                        {
                         "x":190.5809052593,
                         "y":0.916254352208171
                        },
                        {
                         "x":0,
                         "y":1.83250870441634
                        }],
                 "rotation":0,
                 "type":"",
                 "visible":true,
                 "width":0,
                 "x":400.403151914972,
                 "y":318.856514568444
                },
                {
                 "height":0,
                 "id":28,
                 "name":"",
                 "polyline":[
                        {
                         "x":0,
                         "y":0
                        },
                        {
                         "x":-0.916254352208171,
                         "y":12.8275609309144
                        },
                        {
                         "x":31.1526479750779,
                         "y":14.6600696353308
                        },
                        {
                         "x":30.2363936228697,
                         "y":-0.916254352208171
                        },
                        {
                         "x":0,
                         "y":-0.916254352208171
                        }],
                 "rotation":0,
                 "type":"",
                 "visible":true,
                 "width":0,
                 "x":481.033534909291,
                 "y":225.398570643211
                },
                {
                 "height":0,
                 "id":29,
                 "name":"",
                 "polyline":[
                        {
                         "x":0,
                         "y":0
                        },
                        {
                         "x":-0.916254352208171,
                         "y":-64.1378046545721
                        },
                        {
                         "x":31.1526479750779,
                         "y":-63.2215503023639
                        },
                        {
                         "x":31.1526479750779,
                         "y":-32.9851566794943
                        },
                        {
                         "x":175.920835623969,
                         "y":-32.9851566794943
                        },
                        {
                         "x":175.004581271761,
                         "y":0
                        },
                        {
                         "x":1.83250870441634,
                         "y":0
                        }],
                 "rotation":0,
                 "type":"",
                 "visible":true,
                 "width":0,
                 "x":624.885468205974,
                 "y":320.689023272861
                },
                {
                 "height":0,
                 "id":30,
                 "name":"",
                 "polyline":[
                        {
                         "x":0,
                         "y":0
                        },
                        {
                         "x":0,
                         "y":13.7438152831226
                        },
                        {
                         "x":112.699285321605,
                         "y":14.6600696353308
                        },
                        {
                         "x":110.866776617189,
                         "y":-0.916254352208171
                        },
                        {
                         "x":0.916254352208171,
                         "y":-0.916254352208171
                        }],
                 "rotation":0,
                 "type":"",
                 "visible":true,
                 "width":0,
                 "x":656.038116181052,
                 "y":226.314824995419
                },
                {
                 "height":0,
                 "id":31,
                 "name":"",
                 "polyline":[
                        {
                         "x":0,
                         "y":0
                        },
                        {
                         "x":0,
                         "y":16.4925783397471
                        },
                        {
                         "x":79.7141286421111,
                         "y":16.4925783397471
                        },
                        {
                         "x":80.6303829943192,
                         "y":0.916254352208171
                        },
                        {
                         "x":-0.916254352208171,
                         "y":0
                        }],
                 "rotation":0,
                 "type":"",
                 "visible":true,
                 "width":0,
                 "x":672.530694520799,
                 "y":192.413413963716
                }],
         "opacity":1,
         "type":"objectgroup",
         "visible":true,
         "width":50,
         "x":0,
         "y":0
        }],
 "nextobjectid":32,
 "orientation":"orthogonal",
 "renderorder":"right-down",
 "tileheight":16,
 "tilesets":[
        {
         "columns":73,
         "firstgid":1,
         "image":"../images/NESSuper3.png",
         "imageheight":358,
         "imagewidth":1242,
         "margin":1,
         "name":"NESSuper3",
         "spacing":1,
         "tilecount":1533,
         "tileheight":16,
         "tilewidth":16
        }],
 "tilewidth":16,
 "version":1,
 "width":50
}
